commol-0.1.0b1.dist-info/METADATA
commol-0.1.0b1.dist-info/WHEEL
commol_rs/__init__.py
commol_rs/commol_rs.cpython-312-aarch64-linux-gnu.so
commol_rs/commol_rs.pyi
commol-0.1.0b1.dist-info/RECORD
