Metadata-Version: 2.4
Name: commol
Version: 0.1.0b1
Requires-Dist: cffi>=2.0,<3.0
Requires-Dist: numpy>=2.4.0,<3.0
Requires-Dist: pint>=0.25.2,<0.26.0
Requires-Dist: pydantic>=2.0,<3.0
Requires-Dist: scikit-learn>=1.8,<2.0
Requires-Dist: seaborn>=0.13.2,<0.14.0
Requires-Dist: maturin>=1.9.1,<1.10.0 ; extra == 'dev'
Requires-Dist: pre-commit>=3.8,<4.0 ; extra == 'dev'
Requires-Dist: pytest>=8.4,<9.0 ; extra == 'dev'
Requires-Dist: pytest-cov>=6.2,<7.0 ; extra == 'dev'
Requires-Dist: ruff>=0.12,<0.13 ; extra == 'dev'
Requires-Dist: twine>=6.2.0,<7.0.0 ; extra == 'dev'
Requires-Dist: ty>=0.0.9,<0.0.10 ; extra == 'dev'
Requires-Dist: vulture>=2.14,<3.0 ; extra == 'dev'
Requires-Dist: mike>=2.0,<3.0 ; extra == 'docs'
Requires-Dist: mkdocs>=1.6,<2.0 ; extra == 'docs'
Requires-Dist: mkdocstrings[python]>=0.26,<1.0 ; extra == 'docs'
Requires-Dist: mkdocs-autorefs>=1.2,<2.0 ; extra == 'docs'
Requires-Dist: mkdocs-material>=9.5,<10.0 ; extra == 'docs'
Provides-Extra: dev
Provides-Extra: docs
Summary: A high-performance compartment modelling library in Rust and Python.
Author-email: "Rafael J. Villanueva Micó" <rjvillan@imm.upv.es>, Carlos Andreu Vilarroig <caranvi1@upv.es>, David Martínez Rodríguez <damarro3@upv.es>
License-Expression: MIT
Requires-Python: >=3.12.0
Project-URL: Homepage, https://github.com/MUNQU/commol
Project-URL: Documentation, https://munqu.github.io/commol
Project-URL: Repository, https://github.com/MUNQU/commol
Project-URL: Bug Tracker, https://github.com/MUNQU/commol/issues
